<?xml version="1.0" encoding="UTF-8"?>
<list xmlns:xsi="http://www.w3.org/2001/XMLSchema-instance" xsi:noNamespaceSchemaLocation="../xsd/route.xsd">
	<route alias="dragonvalley_2321_01_02event" move_type="MoveSuperPoint_FollowRail">
		<node id="0" x="101836" y="110692" z="-3672" />
		<node id="1" x="101809" y="111329" z="-3680" />
		<node id="2" x="101876" y="112314" z="-3672" />
		<node id="3" x="101555" y="114048" z="-3720" />
		<node id="4" x="101294" y="114920" z="-3720" />
		<node id="5" x="101425" y="116844" z="-3696" />
		<node id="6" x="101971" y="117961" z="-3664" />
		<node id="7" x="102209" y="119530" z="-3600" />
		<node id="8" x="102558" y="120842" z="-3616" />
		<node id="9" x="102574" y="122127" z="-3640" />
		<node id="10" x="102779" y="122899" z="-3640" />
		<node id="11" x="103664" y="123988" z="-3720" />
		<node id="12" x="104928" y="124084" z="-3712" />
		<node id="13" x="106017" y="123573" z="-3656" />
		<node id="14" x="107254" y="122694" z="-3680" />
		<node id="15" x="108439" y="122386" z="-3664" />
		<node id="16" x="109635" y="122366" z="-3672" />
		<node id="17" x="110045" y="122171" z="-3664" />
		<node id="18" x="110483" y="121931" z="-3688" />
	</route>
</list>