<?xml version="1.0" encoding="UTF-8"?>
<list xmlns:xsi="http://www.w3.org/2001/XMLSchema-instance" xsi:noNamespaceSchemaLocation="../xsd/route.xsd">
	<route alias="genesis_GA_line1" move_type="MoveSuperPoint_FollowRail" isRunning="true">
		<node id="0" x="207935" y="119321" z="-1304" />
		<node id="1" x="207940" y="118884" z="-1304" />
		<node id="2" x="207945" y="118353" z="-1304" />
		<node id="3" x="208278" y="118021" z="-1304" />
		<node id="4" x="208584" y="117705" z="-1304" />
		<node id="5" x="209551" y="117679" z="-1304" />
	</route>
</list>