<?xml version="1.0" encoding="UTF-8"?>
<list xmlns:xsi="http://www.w3.org/2001/XMLSchema-instance" xsi:noNamespaceSchemaLocation="../xsd/route.xsd">
	<route alias="lost_62" move_type="MoveSuperPoint_Random">
		<node id="0" x="27148" y="-11204" z="-2400" />
		<node id="1" x="26966" y="-10584" z="-2408" />
		<node id="2" x="26180" y="-10780" z="-2464" />
		<node id="3" x="26367" y="-11535" z="-2480" />
		<node id="4" x="27000" y="-11565" z="-2416" />
		<node id="5" x="26685" y="-11087" z="-2456" />
	</route>
</list>