<?xml version="1.0" encoding="UTF-8"?>
<list xmlns:xsi="http://www.w3.org/2001/XMLSchema-instance" xsi:noNamespaceSchemaLocation="../xsd/route.xsd">
	<route alias="ru_go_fort_ordery" move_type="MoveSuperPoint_FollowRail">
		<node id="0" x="104686" y="-57581" z="-936" />
		<node id="1" x="105438" y="-58455" z="-1112" />
		<node id="2" x="105569" y="-58872" z="-1224" />
		<node id="3" x="106186" y="-59265" z="-1328" />
		<node id="4" x="106866" y="-59434" z="-1624" />
		<node id="5" x="107457" y="-60476" z="-2136" />
		<node id="6" x="107688" y="-61206" z="-2424" />
		<node id="7" x="108320" y="-61927" z="-2952" />
		<node id="8" x="109008" y="-62615" z="-3232" />
		<node id="9" x="108345" y="-62690" z="-3120" />
		<node id="10" x="106944" y="-62153" z="-2984" />
		<node id="11" x="105330" y="-61391" z="-2680" />
		<node id="12" x="103592" y="-60301" z="-2392" />
		<node id="13" x="102979" y="-59855" z="-2384" />
		<node id="14" x="101453" y="-59964" z="-2544" />
	</route>
</list>