<?xml version="1.0" encoding="UTF-8"?>
<list xmlns:xsi="http://www.w3.org/2001/XMLSchema-instance" xsi:noNamespaceSchemaLocation="../xsd/route.xsd">
	<route alias="sf_wire_line2" move_type="MoveSuperPoint_FollowRail">
		<node id="0" x="-105334" y="49691" z="-1816" />
		<node id="1" x="-105507" y="49661" z="-1800" />
		<node id="2" x="-105663" y="49568" z="-1784" />
		<node id="3" x="-105723" y="49416" z="-1784" />
		<node id="4" x="-105749" y="49255" z="-1768" />
		<node id="5" x="-105662" y="49075" z="-1776" />
	</route>
</list>