<?xml version="1.0" encoding="UTF-8"?>
<list xmlns:xsi="http://www.w3.org/2001/XMLSchema-instance" xsi:noNamespaceSchemaLocation="../../xsd/spawns.xsd">
	<spawn name="lyonn10_1914_01m1">
		<territories>
			<territory name="lyonn10_1914_01" minZ="-3255" maxZ="-2855">
				<node x="-13027" y="-123217" />
				<node x="-12884" y="-123148" />
				<node x="-12800" y="-123076" />
				<node x="-12730" y="-123006" />
				<node x="-12703" y="-122928" />
				<node x="-12669" y="-122831" />
				<node x="-12652" y="-122736" />
				<node x="-12658" y="-122625" />
				<node x="-12695" y="-122485" />
				<node x="-12754" y="-122394" />
				<node x="-12817" y="-122299" />
				<node x="-12941" y="-122249" />
				<node x="-13065" y="-122249" />
				<node x="-13160" y="-122238" />
				<node x="-13280" y="-122260" />
				<node x="-13402" y="-122302" />
				<node x="-13528" y="-122430" />
				<node x="-13616" y="-122494" />
				<node x="-13629" y="-122709" />
				<node x="-13631" y="-122833" />
				<node x="-13581" y="-122981" />
				<node x="-13482" y="-123066" />
				<node x="-13394" y="-123115" />
				<node x="-13321" y="-123160" />
				<node x="-13224" y="-123190" />
			</territory>
		</territories>
		<npc id="23330" respawnTime="60sec" count="5" /> <!-- Rubble -->
		<npc id="23333" respawnTime="60sec" count="3" /> <!-- Putrefied Zombie -->
		<npc id="23334" respawnTime="60sec" count="10" /> <!-- Shelop -->
		<npc id="23335" respawnTime="60sec" count="3" /> <!-- Poras -->
		<npc id="23336" respawnTime="60sec" count="3" /> <!-- Death Worm -->
		<npc id="23337" respawnTime="60sec" count="7" /> <!-- Large Rubble -->
	</spawn>
	<spawn name="lyonn10_1914_02m1">
		<territories>
			<territory name="lyonn10_1914_02" minZ="-3622" maxZ="-3222">
				<node x="-14061" y="-118889" />
				<node x="-13995" y="-119020" />
				<node x="-13903" y="-119115" />
				<node x="-13811" y="-119163" />
				<node x="-13721" y="-119191" />
				<node x="-13625" y="-119206" />
				<node x="-13452" y="-119194" />
				<node x="-13343" y="-119122" />
				<node x="-13253" y="-119019" />
				<node x="-13189" y="-118876" />
				<node x="-13133" y="-118742" />
				<node x="-13148" y="-118586" />
				<node x="-13186" y="-118459" />
				<node x="-13291" y="-118327" />
				<node x="-13414" y="-118257" />
				<node x="-13575" y="-118235" />
				<node x="-13758" y="-118216" />
				<node x="-13865" y="-118288" />
				<node x="-13968" y="-118380" />
				<node x="-14043" y="-118500" />
				<node x="-14130" y="-118665" />
			</territory>
		</territories>
		<npc id="23330" respawnTime="60sec" count="5" /> <!-- Rubble -->
		<npc id="23333" respawnTime="60sec" count="3" /> <!-- Putrefied Zombie -->
		<npc id="23334" respawnTime="60sec" count="10" /> <!-- Shelop -->
		<npc id="23335" respawnTime="60sec" count="3" /> <!-- Poras -->
		<npc id="23336" respawnTime="60sec" count="3" /> <!-- Death Worm -->
		<npc id="23337" respawnTime="60sec" count="7" /> <!-- Large Rubble -->
	</spawn>
	<spawn name="lyonn10_1914_03m1">
		<territories>
			<territory name="lyonn10_1914_03" minZ="-3411" maxZ="-3011">
				<node x="-17038" y="-123329" />
				<node x="-16814" y="-123330" />
				<node x="-16679" y="-123283" />
				<node x="-16551" y="-123209" />
				<node x="-16457" y="-123088" />
				<node x="-16388" y="-122968" />
				<node x="-16358" y="-122811" />
				<node x="-16433" y="-122620" />
				<node x="-16514" y="-122508" />
				<node x="-16584" y="-122414" />
				<node x="-16687" y="-122360" />
				<node x="-16821" y="-122359" />
				<node x="-16961" y="-122372" />
				<node x="-17109" y="-122408" />
				<node x="-17224" y="-122479" />
				<node x="-17314" y="-122589" />
				<node x="-17340" y="-122744" />
				<node x="-17359" y="-122898" />
				<node x="-17325" y="-123033" />
				<node x="-17232" y="-123192" />
			</territory>
		</territories>
		<npc id="23330" respawnTime="60sec" count="5" /> <!-- Rubble -->
		<npc id="23333" respawnTime="60sec" count="3" /> <!-- Putrefied Zombie -->
		<npc id="23334" respawnTime="60sec" count="10" /> <!-- Shelop -->
		<npc id="23335" respawnTime="60sec" count="3" /> <!-- Poras -->
		<npc id="23336" respawnTime="60sec" count="3" /> <!-- Death Worm -->
		<npc id="23337" respawnTime="60sec" count="7" /> <!-- Large Rubble -->
	</spawn>
	<spawn name="lyonn10_1914_04m1">
		<territories>
			<territory name="lyonn10_1914_04" minZ="-3868" maxZ="-3468">
				<node x="-14294" y="-115309" />
				<node x="-14254" y="-115413" />
				<node x="-14186" y="-115477" />
				<node x="-14074" y="-115548" />
				<node x="-13879" y="-115638" />
				<node x="-13725" y="-115648" />
				<node x="-13574" y="-115594" />
				<node x="-13408" y="-115457" />
				<node x="-13288" y="-115346" />
				<node x="-13267" y="-115158" />
				<node x="-13306" y="-114972" />
				<node x="-13439" y="-114829" />
				<node x="-13591" y="-114701" />
				<node x="-13763" y="-114646" />
				<node x="-13964" y="-114663" />
				<node x="-14085" y="-114735" />
				<node x="-14174" y="-114853" />
				<node x="-14237" y="-114996" />
				<node x="-14276" y="-115095" />
			</territory>
		</territories>
		<npc id="23330" respawnTime="60sec" count="5" /> <!-- Rubble -->
		<npc id="23333" respawnTime="60sec" count="3" /> <!-- Putrefied Zombie -->
		<npc id="23334" respawnTime="60sec" count="10" /> <!-- Shelop -->
		<npc id="23335" respawnTime="60sec" count="3" /> <!-- Poras -->
		<npc id="23336" respawnTime="60sec" count="3" /> <!-- Death Worm -->
		<npc id="23337" respawnTime="60sec" count="7" /> <!-- Large Rubble -->
	</spawn>
	<spawn name="lyonn10_1914_05m1">
		<territories>
			<territory name="lyonn10_1914_05" minZ="-3632" maxZ="-3232">
				<node x="-14708" y="-110631" />
				<node x="-14620" y="-110555" />
				<node x="-14554" y="-110459" />
				<node x="-14482" y="-110328" />
				<node x="-14455" y="-110217" />
				<node x="-14476" y="-110107" />
				<node x="-14574" y="-109944" />
				<node x="-14659" y="-109857" />
				<node x="-14790" y="-109766" />
				<node x="-14914" y="-109729" />
				<node x="-15066" y="-109735" />
				<node x="-15201" y="-109733" />
				<node x="-15323" y="-109778" />
				<node x="-15400" y="-109912" />
				<node x="-15447" y="-110077" />
				<node x="-15480" y="-110204" />
				<node x="-15446" y="-110340" />
				<node x="-15364" y="-110475" />
				<node x="-15264" y="-110579" />
				<node x="-15161" y="-110687" />
				<node x="-15015" y="-110696" />
				<node x="-14861" y="-110691" />
			</territory>
		</territories>
		<npc id="23330" respawnTime="60sec" count="5" /> <!-- Rubble -->
		<npc id="23333" respawnTime="60sec" count="3" /> <!-- Putrefied Zombie -->
		<npc id="23334" respawnTime="60sec" count="10" /> <!-- Shelop -->
		<npc id="23335" respawnTime="60sec" count="3" /> <!-- Poras -->
		<npc id="23336" respawnTime="60sec" count="3" /> <!-- Death Worm -->
		<npc id="23337" respawnTime="60sec" count="7" /> <!-- Large Rubble -->
	</spawn>
	<spawn name="lyonn10_1914_06m1">
		<territories>
			<territory name="lyonn10_1914_06" minZ="-3637" maxZ="-3237">
				<node x="-21165" y="-111744" />
				<node x="-21098" y="-111908" />
				<node x="-20994" y="-112028" />
				<node x="-20909" y="-112093" />
				<node x="-20797" y="-112132" />
				<node x="-20641" y="-112152" />
				<node x="-20503" y="-112143" />
				<node x="-20342" y="-112062" />
				<node x="-20257" y="-111945" />
				<node x="-20181" y="-111795" />
				<node x="-20185" y="-111617" />
				<node x="-20219" y="-111463" />
				<node x="-20273" y="-111357" />
				<node x="-20354" y="-111240" />
				<node x="-20528" y="-111177" />
				<node x="-20693" y="-111160" />
				<node x="-20860" y="-111204" />
				<node x="-21006" y="-111280" />
				<node x="-21093" y="-111429" />
				<node x="-21146" y="-111581" />
			</territory>
		</territories>
		<npc id="23330" respawnTime="60sec" count="5" /> <!-- Rubble -->
		<npc id="23333" respawnTime="60sec" count="3" /> <!-- Putrefied Zombie -->
		<npc id="23334" respawnTime="60sec" count="10" /> <!-- Shelop -->
		<npc id="23335" respawnTime="60sec" count="3" /> <!-- Poras -->
		<npc id="23336" respawnTime="60sec" count="3" /> <!-- Death Worm -->
		<npc id="23337" respawnTime="60sec" count="7" /> <!-- Large Rubble -->
	</spawn>
	<spawn name="lyonn10_1914_07m1">
		<territories>
			<territory name="lyonn10_1914_07" minZ="-3624" maxZ="-3224">
				<node x="-23969" y="-115937" />
				<node x="-23854" y="-115936" />
				<node x="-23729" y="-115921" />
				<node x="-23560" y="-115856" />
				<node x="-23432" y="-115737" />
				<node x="-23345" y="-115605" />
				<node x="-23277" y="-115451" />
				<node x="-23341" y="-115311" />
				<node x="-23400" y="-115190" />
				<node x="-23531" y="-115057" />
				<node x="-23663" y="-114953" />
				<node x="-23833" y="-114941" />
				<node x="-23994" y="-114993" />
				<node x="-24136" y="-115084" />
				<node x="-24257" y="-115243" />
				<node x="-24286" y="-115471" />
				<node x="-24242" y="-115642" />
				<node x="-24178" y="-115760" />
			</territory>
		</territories>
		<npc id="23330" respawnTime="60sec" count="5" /> <!-- Rubble -->
		<npc id="23333" respawnTime="60sec" count="3" /> <!-- Putrefied Zombie -->
		<npc id="23334" respawnTime="60sec" count="10" /> <!-- Shelop -->
		<npc id="23335" respawnTime="60sec" count="3" /> <!-- Poras -->
		<npc id="23336" respawnTime="60sec" count="3" /> <!-- Death Worm -->
		<npc id="23337" respawnTime="60sec" count="7" /> <!-- Large Rubble -->
	</spawn>
	<spawn name="lyonn10_1914_08m1">
		<territories>
			<territory name="lyonn10_1914_08" minZ="-3515" maxZ="-3115">
				<node x="-23209" y="-120816" />
				<node x="-23037" y="-120866" />
				<node x="-22892" y="-120848" />
				<node x="-22805" y="-120803" />
				<node x="-22717" y="-120705" />
				<node x="-22616" y="-120610" />
				<node x="-22587" y="-120488" />
				<node x="-22569" y="-120351" />
				<node x="-22596" y="-120156" />
				<node x="-22681" y="-120025" />
				<node x="-22829" y="-119914" />
				<node x="-22982" y="-119860" />
				<node x="-23127" y="-119868" />
				<node x="-23267" y="-119936" />
				<node x="-23400" y="-120043" />
				<node x="-23512" y="-120191" />
				<node x="-23523" y="-120358" />
				<node x="-23491" y="-120495" />
				<node x="-23419" y="-120650" />
				<node x="-23327" y="-120764" />
			</territory>
		</territories>
		<npc id="23330" respawnTime="60sec" count="5" /> <!-- Rubble -->
		<npc id="23333" respawnTime="60sec" count="3" /> <!-- Putrefied Zombie -->
		<npc id="23334" respawnTime="60sec" count="10" /> <!-- Shelop -->
		<npc id="23335" respawnTime="60sec" count="3" /> <!-- Poras -->
		<npc id="23336" respawnTime="60sec" count="3" /> <!-- Death Worm -->
		<npc id="23337" respawnTime="60sec" count="7" /> <!-- Large Rubble -->
	</spawn>
	<spawn name="lyonn10_1914_09m1">
		<territories>
			<territory name="lyonn10_1914_09" minZ="-3407" maxZ="-3007">
				<node x="-25983" y="-125084" />
				<node x="-26065" y="-124979" />
				<node x="-26106" y="-124846" />
				<node x="-26090" y="-124703" />
				<node x="-26006" y="-124551" />
				<node x="-25906" y="-124441" />
				<node x="-25719" y="-124361" />
				<node x="-25542" y="-124347" />
				<node x="-25370" y="-124363" />
				<node x="-25219" y="-124474" />
				<node x="-25118" y="-124613" />
				<node x="-25109" y="-124806" />
				<node x="-25153" y="-124980" />
				<node x="-25233" y="-125093" />
				<node x="-25364" y="-125207" />
				<node x="-25507" y="-125265" />
				<node x="-25686" y="-125244" />
				<node x="-25860" y="-125182" />
				<node x="-25971" y="-125104" />
			</territory>
		</territories>
		<npc id="23330" respawnTime="60sec" count="5" /> <!-- Rubble -->
		<npc id="23333" respawnTime="60sec" count="3" /> <!-- Putrefied Zombie -->
		<npc id="23334" respawnTime="60sec" count="10" /> <!-- Shelop -->
		<npc id="23335" respawnTime="60sec" count="3" /> <!-- Poras -->
		<npc id="23336" respawnTime="60sec" count="3" /> <!-- Death Worm -->
		<npc id="23337" respawnTime="60sec" count="7" /> <!-- Large Rubble -->
	</spawn>
	<spawn name="lyonn10_1914_10m1">
		<territories>
			<territory name="lyonn10_1914_10" minZ="-3175" maxZ="-2775">
				<node x="-21726" y="-123576" />
				<node x="-21784" y="-123702" />
				<node x="-21831" y="-123854" />
				<node x="-21873" y="-123979" />
				<node x="-21891" y="-124148" />
				<node x="-21850" y="-124272" />
				<node x="-21748" y="-124387" />
				<node x="-21589" y="-124498" />
				<node x="-21440" y="-124541" />
				<node x="-21282" y="-124543" />
				<node x="-21088" y="-124481" />
				<node x="-20967" y="-124382" />
				<node x="-20902" y="-124200" />
				<node x="-20959" y="-123995" />
				<node x="-21087" y="-124001" />
				<node x="-21195" y="-123903" />
				<node x="-21207" y="-123811" />
				<node x="-21153" y="-123665" />
				<node x="-21323" y="-123584" />
				<node x="-21524" y="-123562" />
			</territory>
		</territories>
		<npc id="23330" respawnTime="60sec" count="5" /> <!-- Rubble -->
		<npc id="23333" respawnTime="60sec" count="3" /> <!-- Putrefied Zombie -->
		<npc id="23334" respawnTime="60sec" count="10" /> <!-- Shelop -->
		<npc id="23335" respawnTime="60sec" count="3" /> <!-- Poras -->
		<npc id="23336" respawnTime="60sec" count="3" /> <!-- Death Worm -->
		<npc id="23337" respawnTime="60sec" count="7" /> <!-- Large Rubble -->
	</spawn>
	<spawn name="Horns" ai="NoRandomActivity">
		<parameters>
			<param name="disableRandomAnimation" value="true" />
			<param name="disableRandomWalk" value="true" />
		</parameters>
		<npc id="19460" x="-12880" y="-115200" z="-3696" heading="0" respawnTime="60sec" /> <!-- Horn -->
		<npc id="19460" x="-14112" y="-110048" z="-3400" heading="0" respawnTime="60sec" /> <!-- Horn -->
		<npc id="19460" x="-15056" y="-111056" z="-3416" heading="0" respawnTime="60sec" /> <!-- Horn -->
		<npc id="19460" x="-15744" y="-110288" z="-3376" heading="0" respawnTime="60sec" /> <!-- Horn -->
		<npc id="19460" x="-14512" y="-115488" z="-3632" heading="0" respawnTime="60sec" /> <!-- Horn -->
		<npc id="19460" x="-19952" y="-111040" z="-3456" heading="0" respawnTime="60sec" /> <!-- Horn -->
		<npc id="19460" x="-21168" y="-112384" z="-3432" heading="0" respawnTime="60sec" /> <!-- Horn -->
		<npc id="19460" x="-21328" y="-111040" z="-3432" heading="0" respawnTime="60sec" /> <!-- Horn -->
		<npc id="19460" x="-24720" y="-115072" z="-3320" heading="0" respawnTime="60sec" /> <!-- Horn -->
		<npc id="19460" x="-23632" y="-116240" z="-3312" heading="0" respawnTime="60sec" /> <!-- Horn -->
		<npc id="19460" x="-23216" y="-114848" z="-3296" heading="0" respawnTime="60sec" /> <!-- Horn -->
		<npc id="19460" x="-22592" y="-119552" z="-3112" heading="0" respawnTime="60sec" /> <!-- Horn -->
		<npc id="19460" x="-24048" y="-120320" z="-3240" heading="0" respawnTime="60sec" /> <!-- Horn -->
		<npc id="19460" x="-24768" y="-124288" z="-2760" heading="0" respawnTime="60sec" /> <!-- Horn -->
		<npc id="19460" x="-26576" y="-124688" z="-2728" heading="0" respawnTime="60sec" /> <!-- Horn -->
		<npc id="19460" x="-22128" y="-123632" z="-3008" heading="0" respawnTime="60sec" /> <!-- Horn -->
		<npc id="19460" x="-20384" y="-123968" z="-3024" heading="0" respawnTime="60sec" /> <!-- Horn -->
		<npc id="19461" x="-14736" y="-113648" z="-3696" heading="0" respawnTime="60sec" /> <!-- Horn -->
		<npc id="19461" x="-14800" y="-113904" z="-3664" heading="0" respawnTime="60sec" /> <!-- Horn -->
		<npc id="19461" x="-14944" y="-113744" z="-3680" heading="0" respawnTime="60sec" /> <!-- Horn -->
		<npc id="19461" x="-15328" y="-113216" z="-3896" heading="0" respawnTime="60sec" /> <!-- Horn -->
		<npc id="19461" x="-16064" y="-111984" z="-3416" heading="0" respawnTime="60sec" /> <!-- Horn -->
		<npc id="19461" x="-16272" y="-116304" z="-4056" heading="0" respawnTime="60sec" /> <!-- Horn -->
		<npc id="19461" x="-16608" y="-116448" z="-4056" heading="0" respawnTime="60sec" /> <!-- Horn -->
		<npc id="19461" x="-16464" y="-115808" z="-4048" heading="0" respawnTime="60sec" /> <!-- Horn -->
		<npc id="19461" x="-16657" y="-111600" z="-3280" heading="0" respawnTime="60sec" /> <!-- Horn -->
		<npc id="19461" x="-17104" y="-111568" z="-3288" heading="0" respawnTime="60sec" /> <!-- Horn -->
		<npc id="19461" x="-16528" y="-111696" z="-3288" heading="0" respawnTime="60sec" /> <!-- Horn -->
		<npc id="19461" x="-20416" y="-112736" z="-3400" heading="0" respawnTime="60sec" /> <!-- Horn -->
		<npc id="19461" x="-20336" y="-112528" z="-3408" heading="0" respawnTime="60sec" /> <!-- Horn -->
		<npc id="19461" x="-22496" y="-114432" z="-3280" heading="0" respawnTime="60sec" /> <!-- Horn -->
		<npc id="19461" x="-22320" y="-113200" z="-3440" heading="0" respawnTime="60sec" /> <!-- Horn -->
		<npc id="19461" x="-21024" y="-114096" z="-4024" heading="0" respawnTime="60sec" /> <!-- Horn -->
		<npc id="19461" x="-20912" y="-114480" z="-4032" heading="0" respawnTime="60sec" /> <!-- Horn -->
		<npc id="19461" x="-20800" y="-114272" z="-4024" heading="0" respawnTime="60sec" /> <!-- Horn -->
		<npc id="19461" x="-20560" y="-112624" z="-3392" heading="0" respawnTime="60sec" /> <!-- Horn -->
		<npc id="19461" x="-23008" y="-113712" z="-3296" heading="0" respawnTime="60sec" /> <!-- Horn -->
		<npc id="19461" x="-23008" y="-113296" z="-3360" heading="0" respawnTime="60sec" /> <!-- Horn -->
		<npc id="19461" x="-23856" y="-111232" z="-3472" heading="0" respawnTime="60sec" /> <!-- Horn -->
		<npc id="19461" x="-23328" y="-110848" z="-3464" heading="0" respawnTime="60sec" /> <!-- Horn -->
		<npc id="19461" x="-22768" y="-110816" z="-3448" heading="0" respawnTime="60sec" /> <!-- Horn -->
		<npc id="19461" x="-23872" y="-111872" z="-3448" heading="0" respawnTime="60sec" /> <!-- Horn -->
		<npc id="19461" x="-23488" y="-109408" z="-3496" heading="0" respawnTime="60sec" /> <!-- Horn -->
		<npc id="19461" x="-23920" y="-109392" z="-3536" heading="0" respawnTime="60sec" /> <!-- Horn -->
		<npc id="19461" x="-23920" y="-108944" z="-3520" heading="0" respawnTime="60sec" /> <!-- Horn -->
		<npc id="19461" x="-23920" y="-110432" z="-3504" heading="0" respawnTime="60sec" /> <!-- Horn -->
		<npc id="19461" x="-23344" y="-110480" z="-3488" heading="0" respawnTime="60sec" /> <!-- Horn -->
		<npc id="19461" x="-22336" y="-115408" z="-3400" heading="0" respawnTime="60sec" /> <!-- Horn -->
		<npc id="19461" x="-22336" y="-114960" z="-3400" heading="0" respawnTime="60sec" /> <!-- Horn -->
		<npc id="19461" x="-22512" y="-114800" z="-3352" heading="0" respawnTime="60sec" /> <!-- Horn -->
		<npc id="19461" x="-23328" y="-118752" z="-3232" heading="0" respawnTime="60sec" /> <!-- Horn -->
		<npc id="19461" x="-23360" y="-117408" z="-3344" heading="0" respawnTime="60sec" /> <!-- Horn -->
		<npc id="19461" x="-23248" y="-118544" z="-3288" heading="0" respawnTime="60sec" /> <!-- Horn -->
		<npc id="19461" x="-23568" y="-117968" z="-3344" heading="0" respawnTime="60sec" /> <!-- Horn -->
		<npc id="19461" x="-21776" y="-117664" z="-4048" heading="0" respawnTime="60sec" /> <!-- Horn -->
		<npc id="19461" x="-21536" y="-117776" z="-4040" heading="0" respawnTime="60sec" /> <!-- Horn -->
		<npc id="19461" x="-21728" y="-117408" z="-4032" heading="0" respawnTime="60sec" /> <!-- Horn -->
		<npc id="19461" x="-23120" y="-118800" z="-3176" heading="0" respawnTime="60sec" /> <!-- Horn -->
		<npc id="19461" x="-24864" y="-122576" z="-2800" heading="0" respawnTime="60sec" /> <!-- Horn -->
		<npc id="19461" x="-25520" y="-122832" z="-2776" heading="0" respawnTime="60sec" /> <!-- Horn -->
		<npc id="19461" x="-24576" y="-122192" z="-2872" heading="0" respawnTime="60sec" /> <!-- Horn -->
		<npc id="19461" x="-21680" y="-122128" z="-3240" heading="0" respawnTime="60sec" /> <!-- Horn -->
		<npc id="19461" x="-21904" y="-122096" z="-3272" heading="0" respawnTime="60sec" /> <!-- Horn -->
		<npc id="19461" x="-21808" y="-122432" z="-3152" heading="0" respawnTime="60sec" /> <!-- Horn -->
		<npc id="19461" x="-21488" y="-122464" z="-3128" heading="0" respawnTime="60sec" /> <!-- Horn -->
		<npc id="19461" x="-25632" y="-123056" z="-2752" heading="0" respawnTime="60sec" /> <!-- Horn -->
		<npc id="19461" x="-24928" y="-122976" z="-2728" heading="0" respawnTime="60sec" /> <!-- Horn -->
		<npc id="19461" x="-23344" y="-124304" z="-2904" heading="0" respawnTime="60sec" /> <!-- Horn -->
		<npc id="19461" x="-23536" y="-124544" z="-2840" heading="0" respawnTime="60sec" /> <!-- Horn -->
		<npc id="19461" x="-23696" y="-124320" z="-2824" heading="0" respawnTime="60sec" /> <!-- Horn -->
		<npc id="19461" x="-23711" y="-122992" z="-2704" heading="0" respawnTime="60sec" /> <!-- Horn -->
		<npc id="19461" x="-24032" y="-123392" z="-2712" heading="0" respawnTime="60sec" /> <!-- Horn -->
		<npc id="19461" x="-23264" y="-123040" z="-2736" heading="0" respawnTime="60sec" /> <!-- Horn -->
		<npc id="19461" x="-19712" y="-123488" z="-3000" heading="0" respawnTime="60sec" /> <!-- Horn -->
		<npc id="19461" x="-19280" y="-122784" z="-2888" heading="0" respawnTime="60sec" /> <!-- Horn -->
		<npc id="19461" x="-19472" y="-122768" z="-2880" heading="0" respawnTime="60sec" /> <!-- Horn -->
		<npc id="19461" x="-19472" y="-122144" z="-2936" heading="0" respawnTime="60sec" /> <!-- Horn -->
		<npc id="19461" x="-20336" y="-120128" z="-4048" heading="0" respawnTime="60sec" /> <!-- Horn -->
		<npc id="19461" x="-20352" y="-119888" z="-4056" heading="0" respawnTime="60sec" /> <!-- Horn -->
		<npc id="19461" x="-20096" y="-120256" z="-4048" heading="0" respawnTime="60sec" /> <!-- Horn -->
		<npc id="19461" x="-18848" y="-119168" z="-4080" heading="0" respawnTime="60sec" /> <!-- Horn -->
		<npc id="19461" x="-19216" y="-119104" z="-4048" heading="0" respawnTime="60sec" /> <!-- Horn -->
		<npc id="19461" x="-19089" y="-119344" z="-4056" heading="0" respawnTime="60sec" /> <!-- Horn -->
		<npc id="19461" x="-24144" y="-107664" z="-3552" heading="0" respawnTime="60sec" /> <!-- Horn -->
		<npc id="19461" x="-24352" y="-107824" z="-3560" heading="0" respawnTime="60sec" /> <!-- Horn -->
		<npc id="19461" x="-24448" y="-107408" z="-3568" heading="0" respawnTime="60sec" /> <!-- Horn -->
		<npc id="19462" x="-13216" y="-115152" z="-3608" heading="0" respawnTime="60sec" /> <!-- Horn -->
		<npc id="19462" x="-14448" y="-110512" z="-3384" heading="0" respawnTime="60sec" /> <!-- Horn -->
		<npc id="19462" x="-21152" y="-111296" z="-3400" heading="0" respawnTime="60sec" /> <!-- Horn -->
		<npc id="19462" x="-24368" y="-115456" z="-3248" heading="0" respawnTime="60sec" /> <!-- Horn -->
		<npc id="19462" x="-23248" y="-119808" z="-3176" heading="0" respawnTime="60sec" /> <!-- Horn -->
		<npc id="19462" x="-25680" y="-124304" z="-2680" heading="0" respawnTime="60sec" /> <!-- Horn -->
		<npc id="19462" x="-22000" y="-124352" z="-2960" heading="0" respawnTime="60sec" /> <!-- Horn -->
		<npc id="19463" x="-13554" y="-116135" z="-3704" heading="62232" respawnTime="60sec" /> <!-- Bloody Horn -->
		<npc id="19463" x="-12618" y="-115727" z="-3688" heading="27294" respawnTime="60sec" /> <!-- Bloody Horn -->
		<npc id="19463" x="-14326" y="-109274" z="-3392" heading="12215" respawnTime="60sec" /> <!-- Bloody Horn -->
		<npc id="19463" x="-17275" y="-115122" z="-4104" heading="13270" respawnTime="60sec" /> <!-- Bloody Horn -->
		<npc id="19463" x="-21529" y="-112773" z="-3496" heading="60101" respawnTime="60sec" /> <!-- Bloody Horn -->
		<npc id="19463" x="-21259" y="-112157" z="-3424" heading="21139" respawnTime="60sec" /> <!-- Bloody Horn -->
		<npc id="19463" x="-23500" y="-116059" z="-3296" heading="20366" respawnTime="60sec" /> <!-- Bloody Horn -->
		<npc id="19463" x="-20659" y="-115209" z="-4056" heading="28544" respawnTime="60sec" /> <!-- Bloody Horn -->
		<npc id="19463" x="-23707" y="-116899" z="-3224" heading="5058" respawnTime="60sec" /> <!-- Bloody Horn -->
		<npc id="19463" x="-21888" y="-121528" z="-3376" heading="4838" respawnTime="60sec" /> <!-- Bloody Horn -->
		<npc id="19463" x="-26351" y="-124548" z="-2696" heading="4127" respawnTime="60sec" /> <!-- Bloody Horn -->
		<npc id="19463" x="-22150" y="-123595" z="-3000" heading="5984" respawnTime="60sec" /> <!-- Bloody Horn -->
		<npc id="19463" x="-26963" y="-123964" z="-2720" heading="32584" respawnTime="60sec" /> <!-- Bloody Horn -->
	</spawn>
	<spawn name="NPCs">
		<npc id="33837" x="-26375" y="-106062" z="-2632" heading="65028" respawnTime="60sec" /> <!-- Refugee Corpse -->
		<npc id="33838" x="-25428" y="-105719" z="-2608" heading="17423" respawnTime="60sec" /> <!-- Quincy -->
		<npc id="33842" x="-25321" y="-105816" z="-2600" heading="23421" respawnTime="60sec" /> <!-- Parajan -->
		<npc id="33843" x="-25517" y="-105892" z="-2600" heading="19380" respawnTime="60sec" /> <!-- Falk -->
	</spawn>
	<spawn name="Legahs">	
		<npc id="19475" x="-14000" y="-115824" z="-3672" heading="0" respawnTime="60sec" /> <!-- Legah -->
		<npc id="19475" x="-13328" y="-114496" z="-3656" heading="0" respawnTime="60sec" /> <!-- Legah -->
		<npc id="19475" x="-14736" y="-110912" z="-3392" heading="0" respawnTime="60sec" /> <!-- Legah -->
		<npc id="19475" x="-14512" y="-109680" z="-3392" heading="0" respawnTime="60sec" /> <!-- Legah -->
		<npc id="19475" x="-15648" y="-110000" z="-3400" heading="0" respawnTime="60sec" /> <!-- Legah -->
		<npc id="19475" x="-14448" y="-114896" z="-3640" heading="5838" respawnTime="60sec" /> <!-- Legah -->
		<npc id="19475" x="-19936" y="-111616" z="-3440" heading="0" respawnTime="60sec" /> <!-- Legah -->
		<npc id="19475" x="-21296" y="-111600" z="-3392" heading="0" respawnTime="60sec" /> <!-- Legah -->
		<npc id="19475" x="-20736" y="-110896" z="-3432" heading="0" respawnTime="60sec" /> <!-- Legah -->
		<npc id="19475" x="-20576" y="-112384" z="-3416" heading="0" respawnTime="60sec" /> <!-- Legah -->
		<npc id="19475" x="-23280" y="-115920" z="-3312" heading="0" respawnTime="60sec" /> <!-- Legah -->
		<npc id="19475" x="-23600" y="-114704" z="-3320" heading="0" respawnTime="60sec" /> <!-- Legah -->
		<npc id="19475" x="-24336" y="-115872" z="-3280" heading="0" respawnTime="60sec" /> <!-- Legah -->
		<npc id="19475" x="-23360" y="-119456" z="-3160" heading="0" respawnTime="60sec" /> <!-- Legah -->
		<npc id="19475" x="-22400" y="-120256" z="-3184" heading="0" respawnTime="60sec" /> <!-- Legah -->
		<npc id="19475" x="-25392" y="-124016" z="-2688" heading="0" respawnTime="60sec" /> <!-- Legah -->
		<npc id="19475" x="-21472" y="-123232" z="-3000" heading="0" respawnTime="60sec" /> <!-- Legah -->
		<npc id="19475" x="-20608" y="-124240" z="-3016" heading="0" respawnTime="60sec" /> <!-- Legah -->
		<npc id="19475" x="-22160" y="-123760" z="-3000" heading="0" respawnTime="60sec" /> <!-- Legah -->
		<npc id="19475" x="-26240" y="-125328" z="-2736" heading="0" respawnTime="60sec" /> <!-- Legah -->
		<npc id="19475" x="-25072" y="-125296" z="-2712" heading="0" respawnTime="60sec" /> <!-- Legah -->
	</spawn>
</list>