<?xml version="1.0" encoding="UTF-8"?>
<list xmlns:xsi="http://www.w3.org/2001/XMLSchema-instance" xsi:noNamespaceSchemaLocation="../../xsd/spawns.xsd">
	<spawn name="ValleyOfTheLords">
		<group>
			<npc id="23351" x="21546" y="-122259" z="-576" heading="41300" respawnTime="60sec" /> <!-- Wild Guardian Tree -->
			<npc id="23351" x="21184" y="-121875" z="-664" heading="19612" respawnTime="60sec" /> <!-- Wild Guardian Tree -->
			<npc id="23351" x="21908" y="-121619" z="-560" heading="3825" respawnTime="60sec" /> <!-- Wild Guardian Tree -->
			<npc id="23351" x="21327" y="-124703" z="-464" heading="28553" respawnTime="60sec" /> <!-- Wild Guardian Tree -->
			<npc id="23351" x="23544" y="-124296" z="-632" heading="25939" respawnTime="60sec" /> <!-- Wild Guardian Tree -->
			<npc id="23351" x="23740" y="-124023" z="-600" heading="51786" respawnTime="60sec" /> <!-- Wild Guardian Tree -->
			<npc id="23351" x="23544" y="-124114" z="-592" heading="5985" respawnTime="60sec" /> <!-- Wild Guardian Tree -->
			<npc id="23351" x="22632" y="-120979" z="-656" heading="24892" respawnTime="60sec" /> <!-- Wild Guardian Tree -->
			<npc id="23351" x="20737" y="-125513" z="-592" heading="13741" respawnTime="60sec" /> <!-- Wild Guardian Tree -->
			<npc id="23351" x="21091" y="-125513" z="-496" heading="11664" respawnTime="60sec" /> <!-- Wild Guardian Tree -->
			<npc id="23351" x="21150" y="-125513" z="-480" heading="36465" respawnTime="60sec" /> <!-- Wild Guardian Tree -->
			<npc id="23351" x="24622" y="-124296" z="-704" heading="20774" respawnTime="60sec" /> <!-- Wild Guardian Tree -->
			<npc id="23351" x="1656" y="-128496" z="-2848" heading="18996" respawnTime="60sec" /> <!-- Wild Guardian Tree -->
			<npc id="23351" x="1656" y="-125200" z="-3256" heading="1623" respawnTime="60sec" /> <!-- Wild Guardian Tree -->
			<npc id="23352" x="21727" y="-122259" z="-600" heading="63591" respawnTime="60sec" /> <!-- Wild Protector Tree -->
			<npc id="23352" x="21546" y="-120979" z="-576" heading="58355" respawnTime="60sec" /> <!-- Wild Protector Tree -->
			<npc id="23352" x="22089" y="-120979" z="-656" heading="33278" respawnTime="60sec" /> <!-- Wild Protector Tree -->
			<npc id="23352" x="21327" y="-124217" z="-536" heading="5420" respawnTime="60sec" /> <!-- Wild Protector Tree -->
			<npc id="23352" x="23838" y="-123841" z="-560" heading="19252" respawnTime="60sec" /> <!-- Wild Protector Tree -->
			<npc id="23352" x="23936" y="-123932" z="-600" heading="19066" respawnTime="60sec" /> <!-- Wild Protector Tree -->
			<npc id="23352" x="22632" y="-121619" z="-656" heading="63596" respawnTime="60sec" /> <!-- Wild Protector Tree -->
			<npc id="23352" x="21209" y="-126647" z="-784" heading="14340" respawnTime="60sec" /> <!-- Wild Protector Tree -->
			<npc id="23352" x="21622" y="-125837" z="-560" heading="7055" respawnTime="60sec" /> <!-- Wild Protector Tree -->
			<npc id="23352" x="20737" y="-125027" z="-496" heading="58454" respawnTime="60sec" /> <!-- Wild Protector Tree -->
			<npc id="23352" x="23152" y="-125206" z="-752" heading="47228" respawnTime="60sec" /> <!-- Wild Protector Tree -->
			<npc id="23352" x="24464" y="-124335" z="-696" heading="7462" respawnTime="60sec" /> <!-- Wild Protector Tree -->
			<npc id="23352" x="16412" y="-128445" z="-2816" heading="26754" respawnTime="60sec" /> <!-- Wild Protector Tree -->
			<npc id="23352" x="16515" y="-127191" z="-2848" heading="26629" respawnTime="60sec" /> <!-- Wild Protector Tree -->
			<npc id="23352" x="16618" y="-126982" z="-2848" heading="30425" respawnTime="60sec" /> <!-- Wild Protector Tree -->
			<npc id="23352" x="17030" y="-128863" z="-2720" heading="25648" respawnTime="60sec" /> <!-- Wild Protector Tree -->
			<npc id="23352" x="1656" y="-128084" z="-2936" heading="62162" respawnTime="60sec" /> <!-- Wild Protector Tree -->
			<npc id="23353" x="21908" y="-122387" z="-632" heading="58331" respawnTime="60sec" /> <!-- Wilderness Protector -->
			<npc id="23353" x="22089" y="-121235" z="-624" heading="60112" respawnTime="60sec" /> <!-- Wilderness Protector -->
			<npc id="23353" x="22451" y="-121875" z="-664" heading="39457" respawnTime="60sec" /> <!-- Wilderness Protector -->
			<npc id="23353" x="21546" y="-121235" z="-568" heading="17534" respawnTime="60sec" /> <!-- Wilderness Protector -->
			<npc id="23353" x="21032" y="-124703" z="-440" heading="20020" respawnTime="60sec" /> <!-- Wilderness Protector -->
			<npc id="23353" x="23936" y="-124023" z="-600" heading="21923" respawnTime="60sec" /> <!-- Wilderness Protector -->
			<npc id="23353" x="23446" y="-124842" z="-688" heading="6338" respawnTime="60sec" /> <!-- Wilderness Protector -->
			<npc id="23353" x="24328" y="-123841" z="-600" heading="44542" respawnTime="60sec" /> <!-- Wilderness Protector -->
			<npc id="23353" x="21327" y="-125837" z="-544" heading="45485" respawnTime="60sec" /> <!-- Wilderness Protector -->
			<npc id="23353" x="21681" y="-126809" z="-880" heading="17107" respawnTime="60sec" /> <!-- Wilderness Protector -->
			<npc id="23353" x="20796" y="-125189" z="-480" heading="56615" respawnTime="60sec" /> <!-- Wilderness Protector -->
			<npc id="23353" x="24793" y="-123847" z="-632" heading="15413" respawnTime="60sec" /> <!-- Wilderness Protector -->
			<npc id="23353" x="1136" y="-128084" z="-3048" heading="14986" respawnTime="60sec" /> <!-- Wilderness Protector -->	
			<npc id="30675" x="19412" y="-118142" z="-3136" heading="0" respawnTime="60sec" /> <!-- Kamuru's Corpse -->
			<npc id="33839" x="14753" y="-120348" z="-1112" heading="12964" respawnTime="60sec" /> <!-- Tuska -->
		</group>
	</spawn>
</list>